pika/__init__.py
pika/amqp_object.py
pika/callback.py
pika/channel.py
pika/compat.py
pika/connection.py
pika/credentials.py
pika/data.py
pika/delivery_mode.py
pika/diagnostic_utils.py
pika/exceptions.py
pika/exchange_type.py
pika/frame.py
pika/heartbeat.py
pika/spec.py
pika/tcp_socket_opts.py
pika/validators.py
pika/adapters/__init__.py
pika/adapters/asyncio_connection.py
pika/adapters/base_connection.py
pika/adapters/blocking_connection.py
pika/adapters/gevent_connection.py
pika/adapters/select_connection.py
pika/adapters/tornado_connection.py
pika/adapters/twisted_connection.py
pika/adapters/utils/__init__.py
pika/adapters/utils/connection_workflow.py
pika/adapters/utils/io_services_utils.py
pika/adapters/utils/nbio_interface.py
pika/adapters/utils/selector_ioloop_adapter.py
pika-1.3.1.dist-info/LICENSE
pika-1.3.1.dist-info/METADATA
pika-1.3.1.dist-info/WHEEL
pika-1.3.1.dist-info/top_level.txt
pika-1.3.1.dist-info/zip-safe
pika-1.3.1.dist-info/RECORD
